extended_hitboxes/__init__.py
extended_hitboxes/algorithms.py
extended_hitboxes/dispatch.py
extended_hitboxes/hitboxes.py
extended_hitboxes-0.2.3.dist-info/licenses/LICENSE
extended_hitboxes-0.2.3.dist-info/METADATA
extended_hitboxes-0.2.3.dist-info/WHEEL
extended_hitboxes-0.2.3.dist-info/top_level.txt
extended_hitboxes-0.2.3.dist-info/RECORD
