Metadata-Version: 2.4
Name: extended-hitboxes
Version: 0.2.3
Summary: A lightweight and extensible 2D collision detection library for Pygame.
Home-page: https://github.com/KeyoneiV/extended-hitboxes
Author: Keyonei Victory
Author-email: vkeyonei@gmail.com
Keywords: pygame collision hitbox 2d game-development library
Classifier: Programming Language :: Python :: 3
Classifier: License :: OSI Approved :: MIT License
Classifier: Operating System :: OS Independent
Classifier: Development Status :: 3 - Alpha
Classifier: Intended Audience :: Developers
Classifier: Topic :: Games/Entertainment
Classifier: Topic :: Software Development :: Libraries :: Python Modules
Requires-Python: >=3.7
License-File: LICENSE
Requires-Dist: pygame>=2.0.0
Dynamic: author
Dynamic: author-email
Dynamic: classifier
Dynamic: description
Dynamic: description-content-type
Dynamic: home-page
Dynamic: keywords
Dynamic: license-file
Dynamic: requires-dist
Dynamic: requires-python
Dynamic: summary
